{
    "www.urbandictionary.com": "",
    "www.hentai-foundry.com": "",
    "www.ver-hentai.online": "",
    "www.vermangasporno.com": "",
    "www.simply-hentai.com": "",
    "www.en.cam.co": "",
    "www.en.cam.com": "",
    "www.bigdickswillingchicks.tumblr.com": "",
    "www.beeg.com": "",
    "www.sextubelinks.com": "",
    "www.xxxbunker.com": "",
    "www.dog.com": "",
    "www.vivthomas.com": "",
    "www.chaturbate.com": "",
    "www.pinkworld.com": "",
    "www.videos-porno.xxxx.com": "",
    "www.uplust.com": "",
    "www.blogfalconstudios.com": "",
    "www.store.falconstudios.com": "",
    "www.hard.pornoxxl.org": "",
    "www.xxl.sexgratuits.com": "",
    "www.xbabe.com": "",
    "www.webpnudes.com": "",
    "www.smutty.com": "",
    "www.pornhubfillesalope.com": "",
    "www.girlygifporn.com": "",
    "www.arabicdancevideo.blogspot.com": "",
    "www.kellydivine.co": "",
    "www.vintagehairy.net": "",
    "www.lookatvintage.com": "",
    "www.roflpot.com": "",
    "www.megamovie.us": "",
    "www.nudeboobshotpics.com": "",
    "www.live.sugarbbw.com": "",
    "www.sexbotbonnasse.com": "",
    "www.popurls.com": "",
    "www.salope.japonsex.com": "",
    "www.milfs.com": "",
    "www.freshmatureporn.com": "",
    "www.matureshine.com": "",
    "www.wetmaturewhores.com": "",
    "www.matures-photos.com": "",
    "www.owsmut.com": "",
    "www.maturestation.com": "",
    "www.webcam.com": "",
    "www.maturelle.com": "",
    "www.womenmaturepics.com": "",
    "www.maturepornhub.com": "",
    "www.hot-naked-milfs.com": "",
    "www.stiflersmoms.com": "",
    "www.matureoracle.com": "",
    "www.hungrymatures.com": "",
    "www.milfous.com": "",
    "www.mom.com": "",
    "www.grannyxxx.co.uk": "",
    "www.maturesinstockings.com": "",
    "www.imaturewomen.com": "",
    "www.wetmaturewomen.com": "",
    "www.riomoms.com": "",
    "www.bitefaim.com": "",
    "www.milfionaire.com": "",
    "www.sexymaturethumbs.com": "",
    "www.mature.com": "",
    "www.golden-moms.com": "",
    "www.motherstits.com": "",
    "www.unshavenpussies.net": "",
    "www.matures.com": "",
    "www.broslingerie.com": "",
    "www.upskirttop.net": "",
    "www.amateurmaturewives.com": "",
    "www.oldernastybitches.com": "",
    "www.maturewant.com": "",
    "www.mulligansmilfs.com": "",
    "www.bestmaturewomen.com": "",
    "www.riomature.com": "",
    "www.inlovewithboobs.com": "",
    "www.mature-women-tube.net": "",
    "www.oldsexybabes.net": "",
    "www.matureplus.com": "",
    "www.matureamour.com": "",
    "www.themomsfucking.net": "",
    "www.boobymilf.com": "",
    "www.fantasticwomans.com": "",
    "www.xxxmaturepost.com": "",
    "www.lenawethole.com": "",
    "www.lfs.com": "",
    "www.wild-matures.com": "",
    "www.horny-matures.net": "",
    "www.grandmabesttube.com": "",
    "www.needmilf.com": "",
    "www.girlmature.com": "",
    "www.bettermilfs.com": "",
    "www.action.com": "",
    "www.babesclub.net": "",
    "www.lovely-mature.net": "",
    "www.bestmaturesthumb.com": "",
    "www.myfreemoms.com": "",
    "www.milfatwork.net": "",
    "www.milfgals.net": "",
    "www.olderwomenarchive.com": "",
    "www.stiflersmilfs.com": "",
    "www.maturenags.com": "",
    "www.maturenakedsluts.com": "",
    "www.tgpmaturewoman.com": "",
    "www.maturewitch.com": "",
    "www.mature-women-tube.org": "",
    "www.lf.com": "",
    "www.booloo.com": "",
    "www.silkymoms.com": "",
    "www.maturedummy.com": "",
    "www.hotfreemilfs.com": "",
    "www.viewmature.com": "",
    "www.momspics.net": "",
    "www.milf-fucking.net": "",
    "www.immoralmatures.com": "",
    "www.matureclithunter.com": "",
    "www.ilovematurewomen.tumblr.com": "",
    "www.matureholes.net": "",
    "www.vipoldies.net": "",
    "www.juicy-matures.com": "",
    "www.hotelmatures.com": "",
    "www.hardsexyyoupornhub.com": "",
    "www.lewd-babes.com": "",
    "www.xxx.adulttube.com": "",
    "www.maturesexy.us": "",
    "www.maturegirl.us": "",
    "www.sexpics.xxx": "",
    "www.ahmilf.com": "",
    "www.indlansex.net": "",
    "www.rat.com": "",
    "www.hen.com": "",
    "www.africansexvideos.net": "",
    "www.bananabunny.com": "",
    "www.cutepornvideos.com": "",
    "www.desimurga.com": "",
    "www.desisexclips.com": "",
    "www.dslady.com": "",
    "www.eroticperfection.com": "",
    "www.es.porn.com": "",
    "www.gaypornium.com": "",
    "www.gracefulnudes.com": "",
    "www.hot-dates.info": "",
    "www.hqlinks.net": "",
    "www.how-do-you-produce-more-seminal-fluid.semenaxx.org": "",
    "www.indianporntube.xxx": "",
    "www.indiansexu.com": "",
    "www.jav-porn.net": "",
    "www.kirtu.com": "",
    "www.legalporno.com": "",
    "www.luboeporno.com": "",
    "www.mypornbookmarks.com": "",
    "www.pinkythekinky.com": "",
    "www.pornfromczech.com": "",
    "www.sexsex.hu": "",
    "www.sexxxxi.com": "",
    "www.shemale.asia": "",
    "www.teengayporntube.com": "",
    "www.thefreecamsecret.com": "",
    "www.theporndude.com": "",
    "www.momsteachsex.com": "",
    "www.videos.petardas.com": "",
    "www.xvideos.com": "",
    "www.adultsextube.com": "",
    "www.alohatube.com": "",
    "www.analsexstars.com": "",
    "www.babosas.com": "",
    "www.bomnporn.com": "",
    "www.brazzers.com": "",
    "www.callboyindia.com": "",
    "www.cam.in": "",
    "www.cholotube.com": "",
    "www.cliphunter.com": "",
    "www.cullosgratis.com": "",
    "www.cumlouder.com": "",
    "www.darering.com": "",
    "www.drtuber.com": "",
    "www.epicporntube.com": "",
    "www.eporner.com": "",
    "www.fapto.xxx": "",
    "www.flirtfree.com": "",
    "www.freeones.com": "",
    "www.freshporn.info": "",
    "www.fuckcuck.com": "",
    "www.gayboystube.com": "",
    "www.fuq.com": "",
    "www.hairy.com": "",
    "www.hindisex.com": "",
    "www.iknowthatgirl.com": "",
    "www.indianpornovid.com": "",
    "www.indianpornvideos.com": "",
    "www.ixxx-tube.com": "",
    "www.ixxx.com": "",
    "www.ixxx.ws": "",
    "www.jizzhut.com": "",
    "www.labatidora.net": "",
    "www.leche.com": "",
    "www.livjasmin.com": "",
    "www.locasporfollar.com": "",
    "www.lushstories.com": "",
    "www.mc-nudes.com": "",
    "www.milfmovs.com": "",
    "www.myfreecams.com": "",
    "www.naughty.com": "",
    "www.penguinvids.com": "",
    "www.perfectgirls.net": "",
    "www.perucaseras.com": "",
    "www.playboy.com": "",
    "www.playvid.com": "",
    "www.pornhub.com": "",
    "www.pornhub.es": "",
    "www.porno.com": "",
    "www.pornorc.net": "",
    "www.porntube.com": "",
    "www.puritanas.com": "",
    "www.redtube.com": "",
    "www.rk.com": "",
    "www.roundandbrown.com": "",
    "www.serviporno.com": "",
    "www.sexocean.com": "",
    "www.teenpornxxx.net": "",
    "www.tnaflix.com": "",
    "www.truthordarepics.com": "",
    "www.tube.com": "",
    "www.tubegalore.com": "",
    "www.videosdemadurasx.com": "",
    "www.watchmygf.com": "",
    "www.x-ho.com": "",
    "www.xixx.com": "",
    "www.xnxx.com": "",
    "www.xtube.com": "",
    "www.xvideosnacional.com": "",
    "www.xxx.com": "",
    "www.youjizz.com": "",
    "www.youporn.com": "",
    "www.xhamster.com": "",
    "www.xhot.sextgem.com": "",
    "www.jeux-flash-sexy.com": "",
    "www.purebbwtube.com": "",
    "www.babes.com": "",
    "www.fotomujeres.pibones.com": "",
    "www.rubber-kingdom.com": "",
    "www.savitabhabhi.mobi": "",
    "www.pinkvisualtgp.com": "",
    "www.antarvasna.com": "",
    "www.hot-gifz.com": "",
    "www.lechecallente.com": "",
    "www.parejasfollando.es": "",
    "www.flirthookup.com": "",
    "www.cerdas.com": "",
    "www.es.chaturbate.com": "",
    "www.youngpornvideos.com": "",
    "www.nudevista.com": "",
    "www.gayboys.com": "",
    "www.pornxxxtubes.com": "",
    "www.ledauphine.com": "",
    "www.freex.mobi": "",
    "www.megavideoporno.org": "",
    "www.pornochaud.com": "",
    "www.gokabyle.com": "",
    "www.bdenjoymore.blogspot.com": "",
    "www.petardas.com": "",
    "www.toroporno.com": "",
    "www.conejox.com": "",
    "www.sambaporno.com": "",
    "www.voyeurpipi.com": "",
    "www.porn.mangassex.com": "",
    "www.goulnes.pornoxxxi.net": "",
    "www.videos-x.xpornogays.com": "",
    "www.indienne-sexy.com": "",
    "www.arabebaise.com": "",
    "www.ohasiatique.com": "",
    "www.porn.com": "",
    "www.xxxonxxx.com": "",
    "www.sexxxdoll.com": "",
    "www.xxxvideosex.org": "",
    "www.gonzoxxxmovies.com": "",
    "www.keezmovies.com": "",
    "www.xxx.xxx": "",
    "www.poringa.net": "",
    "www.videosxxxputas.xxx": "",
    "www.lisaannlovers.tumblr.com": "",
    "www.ht.to": "",
    "www.premiercastingporno.com": "",
    "www.marocainenue.com": "",
    "www.fr.perfectgirls.net": "",
    "www.jeffdunhamfuckdoll.com": "",
    "www.pornmotion.com": "",
    "www.gorgeousladies.com": "",
    "www.fille-nue-video.com": "",
    "www.teensnow.com": "",
    "www.theofficiallouisejenson.com": "",
    "www.bangbros.com": "",
    "www.yourather.com": "",
    "www.bootlus.com": "",
    "www.toonztube.com": "",
    "www.top-chatroulette.com": "",
    "www.videosfilleschaudes.com": "",
    "www.fillechaude.com": "",
    "www.femmesmuresx.net": "",
    "www.liberteenage.com": "",
    "www.coffetube.com": "",
    "www.awesomeellalove.tumblr.com": "",
    "www.xnxxgifs.com": "",
    "www.gaygautemela.com": "",
    "www.saoulbafjojo.com": "",
    "www.pornofemmeblack.com": "",
    "www.sexonapria.org": "",
    "www.beurettehot.net": "",
    "www.woodstockreborn.tumblr.com": "",
    "www.freesex.com": "",
    "www.peliculaspornogratisxxx.com": "",
    "www.porno-algerienne.com": "",
    "www.belles-femmes-arabes.blogspot.com": "",
    "www.lesbiennesxxx.com": "",
    "www.des-filles-sexy.com": "",
    "www.videos-porno-chaudes.com": "",
    "www.xgouines.com": "",
    "www.couleurivoire.com": "",
    "www.animalsextube.com": "",
    "www.moncotube.net": "",
    "www.mouparkstreet.blogspot.com": "",
    "www.sexcoachapp.com": "",
    "www.femdomecpire.com": "",
    "www.babosas.co": "",
    "www.guide-asie.com": "",
    "www.beauxcul.com": "",
    "www.maghrebinnes.xl.cx": "",
    "www.axnxxx.org": "",
    "www.xnxx-free.net": "",
    "www.xnxx.vc": "",
    "www.es.bravotube.net": "",
    "www.femmesporno.com": "",
    "www.tubeduporno.com": "",
    "www.videos-sexe.touffe.com": "",
    "www.video-porno.videurdecouilles.com": "",
    "www.rubias.com": "",
    "www.xxi.onxxille.com": "",
    "www.asiatique-femme.com": "",
    "www.masalopeblack.com": "",
    "www.beautyandthebeard.tumblr.com": "",
    "www.beautiful-nude-teens-exposed.tumblr.com": "",
    "www.porno-marocaine.com": "",
    "www.rueporno.com": "",
    "www.fuckmycheatingslutwife.tumblr.com": "",
    "www.arabe-sexy.com": "",
    "www.film-porno-black.com": "",
    "www.sexe-evbony.com": "",
    "www.gratishentai.net": "",
    "www.cochonnevideosx.com": "",
    "www.chaudassedusexe.com": "",
    "www.videosanalesx.com": "",
    "www.pornotantique.com": "",
    "www.dorceltv.xn.pl": "",
    "www.video-sex.femmesx.net": "",
    "www.boutique-sexy.ch": "",
    "www.salope-marocaine.com": "",
    "www.pornocolumbia.co": "",
    "www.jeunette.com": "",
    "www.sexeasiatique.com": "",
    "www.redtuve.com": "",
    "www.les-groses.net": "",
    "www.nexxx.com": "",
    "www.videospornonacional.com": "",
    "www.xxxkinky.com": "",
    "www.yasminramos.com": "",
    "www.tukif.com": "",
    "www.porno-wife.com": "",
    "www.film-xxx-black.com": "",
    "www.sex.com": "",
    "www.every-seconds.tumblr.com": "",
    "www.adultwork.com": "",
    "www.tendance-lesbienne.com": "",
    "www.jpangel.tumblr.com": "",
    "www.teensexposed.tumblr.com": "",
    "www.girthyencounters.tumblr.com": "",
    "www.cuckinohio.tumblr.com": "",
    "www.dildosatisfaction.tumblr.com": "",
    "www.stretchedpussy.tumblr.com": "",
    "www.mindslostinlust.tumblr.com": "",
    "www.whoresmilfsdegraded.tumblr.com": "",
    "www.indiansexstories.net": "",
    "www.eros.com": "",
    "www.brazzersnetwork.com": "",
    "www.porn.org": "",
    "www.teensnowxvideos.com": "",
    "www.x-art.com": "",
    "www.pandamovies.com": "",
    "www.muyzorras.com": "",
    "www.shemales.com": "",
    "www.bigboobsalert.com": "",
    "www.culx.org": "",
    "www.gay.com": "",
    "www.premium.gays.com": "",
    "www.omegaporno.com": "",
    "www.specialgays.com": "",
    "www.gggay.com": "",
    "www.nautilix.com": "",
    "www.ovideox.com": "",
    "www.aztecaporno.com": "",
    "www.pornosfilms.com": "",
    "www.herbalviagraworld.com": "",
    "www.primecurves.com": "",
    "www.hornybook.com": "",
    "www.pinsex.com": "",
    "www.dreammovies.com": "",
    "www.tubepornstars.com": "",
    "www.pornorama.com": "",
    "www.assall.com": "",
    "www.cindymovies.com": "",
    "www.jizzle.com": "",
    "www.onlygirlvideos.com": "",
    "www.spankwire.com": "",
    "www.arabesexy.com": "",
    "www.nakedboobs.net": "",
    "www.teencamvids.org": "",
    "www.nudematurewomenphotos.com": "",
    "www.eroticbeauties.net": "",
    "www.mature-galleries.org": "",
    "www.all-free-nude-old-granny-mature-women-xxx-porn-pics.com": "",
    "www.nudeold.com": "",
    "www.uniquesexymoms.com": "",
    "www.nude-oldies.com": "",
    "www.multimature.com": "",
    "www.oldhotmoms.com": "",
    "www.watchersweb.com": "",
    "www.eromatures.net": "",
    "www.matureandyoung.com": "",
    "www.momshere.com": "",
    "www.kissmaturesgo.com": "",
    "www.maturosexy.com": "",
    "www.hotnakedoldies.com": "",
    "www.madmamas.com": "",
    "www.womanolder.com": "",
    "www.matureland.net": "",
    "www.pornmaturepics.com": "",
    "www.momstaboo.com": "",
    "www.elderly-women.com": "",
    "www.bushypussies.net": "",
    "www.universeold.com": "",
    "www.unshavengirls.net": "",
    "www.juliepost.com": "",
    "www.mature-orgasm.com": "",
    "www.riotits.net": "",
    "www.nakedbustytits.com": "",
    "www.ass-butt.com": "",
    "www.matureladiespics.com": "",
    "www.pornmaturewomen.com": "",
    "www.nudemomphotos.com": "",
    "www.secinsurance.com": "",
    "www.bigfreemature.com": "",
    "www.hotnudematures.com": "",
    "www.matureasspics.com": "",
    "www.alloldpics.com": "",
    "www.mature.nl": "",
    "www.wifezilla.com": "",
    "www.chubbygalls.com": "",
    "www.nudematurespics.com": "",
    "www.matureal.com": "",
    "www.thexmilf.com": "",
    "www.cocom": "",
    "www.zmilfs.com": "",
    "www.bestmilftube.com": "",
    "www.bestmatureclips.com": "",
    "www.lustfuloldies.com": "",
    "www.maturehotsex.com": "",
    "www.oldercherry.com": "",
    "www.sexymilfpussy.com": "",
    "www.maturepornpics.com": "",
    "www.dianapost.com": "",
    "www.milfmomspics.com": "",
    "www.pornovideo.italy.com": "",
    "www.idealwifes.com": "",
    "www.hqmaturemovs.com": "",
    "www.olderwomentaboo.com": "",
    "www.chocom": "",
    "www.milfparanoia.com": "",
    "www.momsnightjob.com": "",
    "www.matureintros.com": "",
    "www.bigbuttmature.com": "",
    "www.maturetube.com": "",
    "www.mature-.com": "",
    "www.maturecool.com": "",
    "www.mamitatube.com": "",
    "www.freematurevideo.net": "",
    "www.momsclan.com": "",
    "www.bravomamas.com": "",
    "www.sharedxpics.com": "",
    "www.fuckmaturewhore.com": "",
    "www.el-ladies.com": "",
    "www.xxxmomclips.com": "",
    "www.idealmilf.com": "",
    "www.alexmatures.com": "",
    "www.kingsizebreasts.com": "",
    "www.matureladies.com": "",
    "www.bigtitsnaked.com": "",
    "www.xebonygirls.com": "",
    "www.numaturewomen.com": "",
    "www.womeninyears.com": "",
    "www.maturehere.com": "",
    "www.milfpicshere.com": "",
    "www.maturepicsarchive.com": "",
    "www.cleomture.com": "",
    "www.maturecherry.net": "",
    "www.pretty-matures.com": "",
    "www.nudematurepussy.com": "",
    "www.nudemomandboy.com": "",
    "www.mygranny.pics": "",
    "www.eroticteens.pw": "",
    "www.pussy-mature.com": "",
    "www.fatsexygirls.net": "",
    "www.somethingmag.com": "",
    "www.amazingmaturesluts.com": "",
    "www.milftubevids.com": "",
    "www.myhdshop.com": "",
    "www.gaytube.com": "",
    "www.galsarchive.com": "",
    "www.mature-for-you.com": "",
    "www.gracefulmilf.com": "",
    "www.momsforporn.com": "",
    "www.sexyhotmilf.com": "",
    "www.azgals.com": "",
    "www.thematureladies.com": "",
    "www.cheatwife.com": "",
    "www.picsboob.com": "",
    "www.agedmamas.com": "",
    "www.bigtitsmilf.com": "",
    "www.mturemomsporn.com": "",
    "www.older-beauty.com": "",
    "www.empflix.com": "",
    "www.numoms.com": "",
    "www.ladymom.com": "",
    "www.petiteporn.pw": "",
    "www.grannyhairy.net": "",
    "www.sexy-olders.com": "",
    "www.nudematuremix.com": "",
    "www.mature-library.com": "",
    "www.filthymamas.com": "",
    "www.sexualolders.com": "",
    "www.horny-olders.com": "",
    "www.olderkiss.com": "",
    "www.wethairywats.com": "",
    "www.erotic-olders.com": "",
    "www.maturemompics.com": "",
    "www.maturedally.net": "",
    "www.place.com": "",
    "www.teenhana.com": "",
    "www.classic-moms.com": "",
    "www.grandmammapics.com": "",
    "www.xmilfpics.com": "",
    "www.hotchicks.sexy": "",
    "www.ebonyfantasies.com": "",
    "www.milfbank.com": "",
    "www.freematurepornpics.com": "",
    "www.agedcunts.net": "",
    "www.milfsection.met": "",
    "www.everydaycams.com": "",
    "www.adultreviews.com": "",
    "www.milfjam.com": "",
    "www.bbwpornpics.com": "",
    "www.pornxxx.com": "",
    "www.milfkiss.com": "",
    "www.chubbygirlpics.com": "",
    "www.hairymaturegirls.com": "",
    "www.pamelapost.com": "",
    "www.feel.net": "",
    "www.tubefellas.com": "",
    "www.sexybuttpics.com": "",
    "www.sexyhotmilfs.com": "",
    "www.secretarypics.com": "",
    "www.naked-moms.com": "",
    "www.momhandjob.com": "",
    "www.pornsticky.com": "",
    "www.hairymilfpics.com": "",
    "www.maturebrotherthumbs.com": "",
    "www.hotmomsporn.com": "",
    "www.plusgirls.com": "",
    "www.wifesbank.com": "",
    "www.milfsarea.com": "",
    "www.pornoriver.net": "",
    "www.milfsbeach.com": "",
    "www.matureguide.com": "",
    "www.dailyolders.com": "",
    "www.askyourmommy.com": "",
    "www.free-porn-pics.net": "",
    "www.maturepornhere.com": "",
    "www.nakedoldbabes.com": "",
    "www.stripping-moms.com": "",
    "www.owerotica.com": "",
    "www.old-vulva.com": "",
    "www.oldmomstgp.com": "",
    "www.posing-matures.com": "",
    "www.momsecstasy.com": "",
    "www.gracefulmom.com": "",
    "www.wetmaturepics.com": "",
    "www.maturexxxclipz.com": "",
    "www.riomilf.com": "",
    "www.fresholders.com": "",
    "www.hqoldies.com": "",
    "www.amateur-libertins.net": "",
    "www.maturepornqueens.net": "",
    "www.myonlyhd.com": "",
    "www.amapics.net": "",
    "www.yomilf.com": "",
    "www.fuckdc.com": "",
    "www.mommyxxxmovies.com": "",
    "www.teenpussy.pw": "",
    "www.imomsex.com": "",
    "www.matureandgranny.com": "",
    "www.milffreepictures.com": "",
    "www.gentlemoms.com": "",
    "www.deviantclip.com": "",
    "www.oldsweet.com": "",
    "www.grannypornpics.net": "",
    "www.lewdmistress.com": "",
    "www.worldxxxphotos.com": "",
    "www.sweetmaturepics.com": "",
    "www.oldpoon.com": "",
    "www.sexymaturepics.com": "",
    "www.goodgrannypics.com": "",
    "www.dagay.com": "",
    "www.randyhags.com": "",
    "www.thegranny.net": "",
    "www.maturemomsex.com": "",
    "www.maturesort.com": "",
    "www.immodestmoms.com": "",
    "www.immaturewomen.com": "",
    "www.bigbotyfree.com": "",
    "www.tiny-cams.com": "",
    "www.oldwomanface.com": "",
    "www.home-madness.com": "",
    "www.posingwomen.com": "",
    "www.maturesensations.com": "",
    "www.filthyoldies.com": "",
    "www.matureclits.net": "",
    "www.momsinporn.net": "",
    "www.maturebabesporno.com": "",
    "www.matureinlove.net": "",
    "www.bigtitsporn.me": "",
    "www.xxxolders.com": "",
    "www.freemilfsite.com": "",
    "www.sex.pornoxxl.org": "",
    "www.queenofmature.com": "",
    "www.hotmomspics.com": "",
    "www.freemilfpornpics.com": "",
    "www.ashleyrnadison.com": "",
    "www.bizzzporno.com": "",
    "www.sexy-links.net": "",
    "www.hotsexyteensphotos.com": "",
    "www.teemns-pic.com": "",
    "www.video-porno.lecheuse.com": "",
    "www.mrskin.com": "",
    "www.gobeurettes.com": "",
    "www.actuallyattractiveamateurs.tumblr.com": "",
    "www.sexynakedamateurgirls.com": "",
    "www.nudedares.tumblr.com": "",
    "www.amateur-sexys.tumblr.com": "",
    "www.hothomemadepix.tumblr.com": "",
    "www.hotamateurclip.com": "",
    "www.voyeursport.com": "",
    "www.upskirt.com": "",
    "www.fakku.net": "",
    "www.pornmirror.com": "",
    "www.youjizz.ws": "",
    "www.insext.net": "",
    "www.pahubad.com": "",
    "www.xtube.nom.co": "",
    "www.boytikol.com": "",
    "www.beeg.co": "",
    "www.khu.biz": "",
    "www.gonzo.com": "",
    "www.esseporn.com": "",
    "www.myfreepornvideos.net": "",
    "www.freeones.ch": "",
    "www.efukt.com": "",
    "www.newsfilter.org": "",
    "www.xxxvideo.com": "",
    "www.video-one.com": "",
    "www.pornstarhangout.com": "",
    "www.breeolson.com": "",
    "www.collegehumor.com": "",
    "www.barstoolsports.com": "",
    "www.hollywoodjizz.com": "",
    "www.shitbrix.com": "",
    "www.xxxsummer.net": "",
    "www.porny.com": "",
    "www.video.freex.mobl": "",
    "www.dixvi.com": "",
    "www.pornnakedgirls.com": "",
    "www.realitypassplus.com": "",
    "www.digitalplayground.com": "",
    "www.kickass.com": "",
    "www.es.xhamster.com": "",
    "www.bravioteens.com": "",
    "www.katestube.com": "",
    "www.yourlust.com": "",
    "www.wixvi.com": "",
    "www.porntubevidz.com": "",
    "www.movs.com": "",
    "www.buzzwok.com": "",
    "www.largepontube.com": "",
    "www.kickass.co": "",
    "www.godao.com": "",
    "www.hardsextube.com": "",
    "www.ah-me.com": "",
    "www.nuvid.com": "",
    "www.pointz.com": "",
    "www.jrunk.tumblr.com": "",
    "www.pornerbros.com": "",
    "www.porndig.com": "",
    "www.bigtinz.com": "",
    "www.nsex.com": "",
    "www.imagefap.com": "",
    "www.adultfriendfinder.com": "",
    "www.pornodoido.com": "",
    "www.hdrolet.com": "",
    "www.xpornking.com": "",
    "www.pornokutusu.com": "",
    "www.pornzz.com": "",
    "www.pornoforo.com": "",
    "www.milfpornet.com": "",
    "www.kink.com": "",
    "www.squirtingmastery.com": "",
    "www.thehotpics.com": "",
    "www.pof.com": "",
    "www.eatyouout.tumblr.com": "",
    "www.milfsaffair.com": "",
    "www.indiangilma.com": "",
    "www.private.com": "",
    "www.fuck-milf.com": "",
    "www.foto-erotica.es": "",
    "www.daultpornvideox.com": "",
    "www.es.bongacams.com": "",
    "www.lastsexe.com": "",
    "www.pinksofa.com": "",
    "www.pinkcupid.com": "",
    "www.onlyporngif.com": "",
    "www.sexyono.com": "",
    "www.motherless.com": "",
    "www.joncjg.blogspot.in": "",
    "www.fr-nostradamus.com": "",
    "www.masturbationaddicton.net": "",
    "www.japanesexxxtube.com": "",
    "www.kilopics.com": "",
    "www.find-best-lingerie.com": "",
    "www.dustyporn.com": "",
    "www.cleoteener.com": "",
    "www.teenass.com": "",
    "www.eternaldesire.com": "",
    "www.sexyteensphotos.com": "",
    "www.teenpornjoy.com": "",
    "www.bubblebuttpics.com": "",
    "www.allofteens.com": "",
    "www.tinysolo.com": "",
    "www.mynakedteens.com": "",
    "www.youngmint.com": "",
    "www.yourlustgirlfriends.com": "",
    "www.youngxxxpics.com": "",
    "www.pinkteenpics.com": "",
    "www.clit.com": "",
    "www.find-best-videos.com": "",
    "www.freekiloclips.com": "",
    "www.nudeartstars.com": "",
    "www.freeporndr.com": "",
    "www.superdiosas.com": "",
    "www.disco-girls.com": "",
    "www.lewd-girls.com": "",
    "www.mega-teen.com": "",
    "www.heganporn.com": "",
    "www.pornstarnirvna.com": "",
    "www.llveleak.com": "",
    "www.rude.com": "",
    "www.anatarvasnavideos.com": "",
    "www.tour.fuckmyindiangf.com": "",
    "www.desindian.sextgem.com": "",
    "www.iscindia.org": "",
    "www.tubegogo.com": "",
    "www.in.spankbang.com": "",
    "www.yehfun.com": "",
    "www.indiankahani.com": "",
    "www.pornmdk.com": "",
    "www.tubestack.com": "",
    "www.desikahani.net": "",
    "www.xesi.mobi": "",
    "www.desitales.com": "",
    "www.allindiansex.com": "",
    "www.tubexclips.com": "",
    "www.boyddl.com": "",
    "www.cmasala.com": "",
    "www.slutload.com": "",
    "www.befuck.com": "",
    "www.allindiansexstories.com": "",
    "www.cinedunia.com": "",
    "www.bollywood-sex.net": "",
    "www.funjadu.com": "",
    "www.iloveindiansex.com": "",
    "www.hyat.mobi": "",
    "www.m.chudaimaza.com": "",
    "www.adultphonechatlines.co.uk": "",
    "www.fsiblog.com": "",
    "www.fucking.com": "",
    "www.cloaktube.com": "",
    "www.indianhotjokes.blogspot.in": "",
    "www.wegret.com": "",
    "www.indiansgoanal.org": "",
    "www.desipapa.com": "",
    "www.alizjokes.blogspot.in": "",
    "www.jlobster.com": "",
    "www.desikamasutra.com": "",
    "www.myhotsite.net": "",
    "www.hindi-sex.net": "",
    "www.bullporn.com": "",
    "www.oigh.info": "",
    "www.jizzporntube.com": "",
    "www.nonvegjokes.com": "",
    "www.eeltube.com": "",
    "www.haporntube.com": "",
    "www.hindiold.com": "",
    "www.gramateurs.com": "",
    "www.fresh-galleries.com": "",
    "www.alansanal.com": "",
    "www.mature-beach.com": "",
    "www.myexmilf.com": "",
    "www.bestmilfsporn.com": "",
    "www.icematures.com": "",
    "www.mature.net": "",
    "www.milfera.com": "",
    "www.excitingmatures.com": "",
    "www.maturedolls.net": "",
    "www.juicygranny.com": "",
    "www.sexymaturepussies.com": "",
    "www.wifenaked.net": "",
    "www.matureplace.com": "",
    "www.bigtitsfree.net": "",
    "www.amaclips.com": "",
    "www.eroticplace.net": "",
    "www.nhentai.com": "",
    "rule34.xxx": "",
    "hentaihaven.xxx": "",
    "hentaihaven.me": "",
    "hentaihaven.red": "",
    "pronhub.com": "",
    "nhentai.net": "",
    "vercomicsporno.com": "",
    "chochox.com": "",
    "paheal.net": "",
    "lesbianas.com": "",
    "hentai-id.tv": "",
    "nekos.life": "",
    "influencinudes.com": "",
    "goku.com": "",
    "sexomoda.com": "",
    "coheteporno.net": "",
    "link4game.com": "",
    "tvsex.com": "",
    "sextv.com": ""
}